<annotation>
	<folder>hp-mouse-X1000</folder>
	<filename>hp-mouse-X1000_36.jpg</filename>
	<path>C:\Users\HP\Desktop\bathrey\edit\hp-mouse-X1000\hp-mouse-X1000_36.jpg</path>
	<source>
		<database>Unknown</database>
	</source>
	<size>
		<width>1920</width>
		<height>1080</height>
		<depth>3</depth>
	</size>
	<segmented>0</segmented>
	<object>
		<name>hp-mouse-X1000</name>
		<pose>Unspecified</pose>
		<truncated>0</truncated>
		<difficult>0</difficult>
		<bndbox>
			<xmin>1127</xmin>
			<ymin>70</ymin>
			<xmax>1886</xmax>
			<ymax>1015</ymax>
		</bndbox>
	</object>
</annotation>
